[
  {
    "time": "2026-01-19T08:00:00Z",
    "cpu_usage": 25,
    "memory_usage": 55,
    "disk_usage": 70,
    "network_in": 120,
    "network_out": 110,
    "service_status": 1
  },
  {
    "time": "2026-01-19T08:05:00Z",
    "cpu_usage": 30,
    "memory_usage": 57,
    "disk_usage": 71,
    "network_in": 130,
    "network_out": 115,
    "service_status": 1
  },
  {
    "time": "2026-01-19T08:10:00Z",
    "cpu_usage": 35,
    "memory_usage": 60,
    "disk_usage": 72,
    "network_in": 140,
    "network_out": 120,
    "service_status": 1
  },
  {
    "time": "2026-01-19T08:15:00Z",
    "cpu_usage": 80,
    "memory_usage": 75,
    "disk_usage": 73,
    "network_in": 250,
    "network_out": 230,
    "service_status": 2
  },
  {
    "time": "2026-01-19T08:20:00Z",
    "cpu_usage": 90,
    "memory_usage": 80,
    "disk_usage": 75,
    "network_in": 300,
    "network_out": 280,
    "service_status": 2
  },
  {
    "time": "2026-01-19T08:25:00Z",
    "cpu_usage": 40,
    "memory_usage": 65,
    "disk_usage": 74,
    "network_in": 150,
    "network_out": 140,
    "service_status": 1
  },
  {
    "time": "2026-01-19T08:30:00Z",
    "cpu_usage": 30,
    "memory_usage": 60,
    "disk_usage": 73,
    "network_in": 130,
    "network_out": 120,
    "service_status": 1
  }
]
